pdisk/__init__.py
pdisk/pdisk.py
pdisk/type.py
pdisk-1.0.6.dist-info/LICENSE
pdisk-1.0.6.dist-info/METADATA
pdisk-1.0.6.dist-info/WHEEL
pdisk-1.0.6.dist-info/top_level.txt
pdisk-1.0.6.dist-info/RECORD
