Metadata-Version: 2.1
Name: pdisk
Version: 1.0.6
Summary: An Unofficial Asynchronous Python version of pdisk API wrapper
Home-page: https://github.com/kalanakt/pdisk
Author: kalanakt
Author-email: kalanakt <kalanakt@uvew.xyz>
License: MIT
Project-URL: Homepage, https://github.com/kalanakt/pdisk
Project-URL: Bug Tracker, https://github.com/kalanakt/pdisk/issues
Keywords: python,pdisk,earn money 
Classifier: Programming Language :: Python :: 3
Classifier: License :: OSI Approved :: MIT License
Classifier: Operating System :: OS Independent
Requires-Python: >=3.7
License-File: LICENSE
Requires-Dist: requests
